NanrenZhenxiang/README.md
NanrenZhenxiang/__init__.py
NanrenZhenxiang/__main__.py
NanrenZhenxiang/file.epub
NanrenZhenxiang/index.html
NanrenZhenxiang/css/__init__.py
NanrenZhenxiang/css/annotations.css
NanrenZhenxiang/css/main.css
NanrenZhenxiang/css/normalize.css
NanrenZhenxiang/css/popup.css
NanrenZhenxiang/font/__init__.py
NanrenZhenxiang/font/fontello.eot
NanrenZhenxiang/font/fontello.svg
NanrenZhenxiang/font/fontello.ttf
NanrenZhenxiang/font/fontello.woff
NanrenZhenxiang/img/__init__.py
NanrenZhenxiang/img/annotator-glyph-sprite.png
NanrenZhenxiang/img/annotator-icon-sprite.png
NanrenZhenxiang/img/apple-touch-icon.png
NanrenZhenxiang/img/cancelfullscreen.png
NanrenZhenxiang/img/close.png
NanrenZhenxiang/img/fullscreen.png
NanrenZhenxiang/img/loader.gif
NanrenZhenxiang/img/menu-icon.png
NanrenZhenxiang/img/save.png
NanrenZhenxiang/img/saved.png
NanrenZhenxiang/img/settings-s.png
NanrenZhenxiang/img/settings.png
NanrenZhenxiang/img/star.png
NanrenZhenxiang/js/__init__.py
NanrenZhenxiang/js/epub.js
NanrenZhenxiang/js/epub.min.js
NanrenZhenxiang/js/epub.min.map
NanrenZhenxiang/js/hooks.min.js
NanrenZhenxiang/js/hooks.min.map
NanrenZhenxiang/js/reader.js
NanrenZhenxiang/js/reader.js.map
NanrenZhenxiang/js/reader.min.js
NanrenZhenxiang/js/reader.min.map
NanrenZhenxiang/js/hooks/__init__.py
NanrenZhenxiang/js/hooks/extensions/__init__.py
NanrenZhenxiang/js/hooks/extensions/highlight.js
NanrenZhenxiang/js/libs/__init__.py
NanrenZhenxiang/js/libs/jquery.min.js
NanrenZhenxiang/js/libs/localforage.min.js
NanrenZhenxiang/js/libs/screenfull.js
NanrenZhenxiang/js/libs/screenfull.min.js
NanrenZhenxiang/js/libs/zip.min.js
NanrenZhenxiang/js/plugins/__init__.py
NanrenZhenxiang/js/plugins/hypothesis.js
NanrenZhenxiang/js/plugins/search.js
nanren_zhenxiang-2022.10.11.0.dist-info/METADATA
nanren_zhenxiang-2022.10.11.0.dist-info/WHEEL
nanren_zhenxiang-2022.10.11.0.dist-info/entry_points.txt
nanren_zhenxiang-2022.10.11.0.dist-info/top_level.txt
nanren_zhenxiang-2022.10.11.0.dist-info/RECORD
